trytond/modules/web_shop_shopify/__init__.py
trytond/modules/web_shop_shopify/account.py
trytond/modules/web_shop_shopify/carrier.py
trytond/modules/web_shop_shopify/carrier.xml
trytond/modules/web_shop_shopify/common.py
trytond/modules/web_shop_shopify/exceptions.py
trytond/modules/web_shop_shopify/graphql.py
trytond/modules/web_shop_shopify/ir.py
trytond/modules/web_shop_shopify/ir.xml
trytond/modules/web_shop_shopify/message.xml
trytond/modules/web_shop_shopify/party.py
trytond/modules/web_shop_shopify/party.xml
trytond/modules/web_shop_shopify/product.py
trytond/modules/web_shop_shopify/product.xml
trytond/modules/web_shop_shopify/routes.py
trytond/modules/web_shop_shopify/sale.py
trytond/modules/web_shop_shopify/sale.xml
trytond/modules/web_shop_shopify/shopify_retry.py
trytond/modules/web_shop_shopify/stock.py
trytond/modules/web_shop_shopify/stock.xml
trytond/modules/web_shop_shopify/tryton.cfg
trytond/modules/web_shop_shopify/web.py
trytond/modules/web_shop_shopify/web.xml
trytond/modules/web_shop_shopify/locale/bg.po
trytond/modules/web_shop_shopify/locale/ca.po
trytond/modules/web_shop_shopify/locale/cs.po
trytond/modules/web_shop_shopify/locale/de.po
trytond/modules/web_shop_shopify/locale/es.po
trytond/modules/web_shop_shopify/locale/es_419.po
trytond/modules/web_shop_shopify/locale/et.po
trytond/modules/web_shop_shopify/locale/fa.po
trytond/modules/web_shop_shopify/locale/fi.po
trytond/modules/web_shop_shopify/locale/fr.po
trytond/modules/web_shop_shopify/locale/hu.po
trytond/modules/web_shop_shopify/locale/id.po
trytond/modules/web_shop_shopify/locale/it.po
trytond/modules/web_shop_shopify/locale/lo.po
trytond/modules/web_shop_shopify/locale/lt.po
trytond/modules/web_shop_shopify/locale/nl.po
trytond/modules/web_shop_shopify/locale/pl.po
trytond/modules/web_shop_shopify/locale/pt.po
trytond/modules/web_shop_shopify/locale/ro.po
trytond/modules/web_shop_shopify/locale/ru.po
trytond/modules/web_shop_shopify/locale/sl.po
trytond_web_shop_shopify-7.8.3.dist-info/licenses/LICENSE
trytond_web_shop_shopify-7.8.3.dist-info/METADATA
trytond_web_shop_shopify-7.8.3.dist-info/WHEEL
trytond_web_shop_shopify-7.8.3.dist-info/entry_points.txt
trytond_web_shop_shopify-7.8.3.dist-info/top_level.txt
trytond_web_shop_shopify-7.8.3.dist-info/RECORD
