Metadata-Version: 2.4
Name: trytond_web_shop_shopify
Version: 7.8.3
Summary: Module to integrate Tryton with Shopify
Home-page: http://www.tryton.org/
Download-URL: http://downloads.tryton.org/7.8/
Author: Tryton
Author-email: foundation@tryton.org
License: GPL-3
Project-URL: Bug Tracker, https://bugs.tryton.org/
Project-URL: Documentation, https://docs.tryton.org/modules-web-shop-shopify
Project-URL: Forum, https://www.tryton.org/forum
Project-URL: Source Code, https://code.tryton.org/tryton
Keywords: web shopify ecommerce
Classifier: Development Status :: 5 - Production/Stable
Classifier: Environment :: Plugins
Classifier: Framework :: Tryton
Classifier: Intended Audience :: Developers
Classifier: Intended Audience :: Financial and Insurance Industry
Classifier: Intended Audience :: Legal Industry
Classifier: License :: OSI Approved :: GNU General Public License v3 or later (GPLv3+)
Classifier: Natural Language :: Bulgarian
Classifier: Natural Language :: Catalan
Classifier: Natural Language :: Chinese (Simplified)
Classifier: Natural Language :: Czech
Classifier: Natural Language :: Dutch
Classifier: Natural Language :: English
Classifier: Natural Language :: Finnish
Classifier: Natural Language :: French
Classifier: Natural Language :: German
Classifier: Natural Language :: Hungarian
Classifier: Natural Language :: Indonesian
Classifier: Natural Language :: Italian
Classifier: Natural Language :: Persian
Classifier: Natural Language :: Polish
Classifier: Natural Language :: Portuguese (Brazilian)
Classifier: Natural Language :: Romanian
Classifier: Natural Language :: Russian
Classifier: Natural Language :: Slovenian
Classifier: Natural Language :: Spanish
Classifier: Natural Language :: Turkish
Classifier: Natural Language :: Ukrainian
Classifier: Operating System :: OS Independent
Classifier: Programming Language :: Python :: 3
Classifier: Programming Language :: Python :: 3.9
Classifier: Programming Language :: Python :: 3.10
Classifier: Programming Language :: Python :: 3.11
Classifier: Programming Language :: Python :: 3.12
Classifier: Programming Language :: Python :: 3.13
Classifier: Programming Language :: Python :: Implementation :: CPython
Classifier: Topic :: Office/Business
Requires-Python: >=3.9
License-File: LICENSE
Requires-Dist: ShopifyAPI
Requires-Dist: pyactiveresource
Requires-Dist: python-sql
Requires-Dist: python-dateutil
Requires-Dist: trytond_account_payment<7.9,>=7.8
Requires-Dist: trytond_currency<7.9,>=7.8
Requires-Dist: trytond_party<7.9,>=7.8
Requires-Dist: trytond_product<7.9,>=7.8
Requires-Dist: trytond_product_attribute<7.9,>=7.8
Requires-Dist: trytond_sale<7.9,>=7.8
Requires-Dist: trytond_sale_amendment<7.9,>=7.8
Requires-Dist: trytond_sale_payment<7.9,>=7.8
Requires-Dist: trytond_stock<7.9,>=7.8
Requires-Dist: trytond_web_shop<7.9,>=7.8
Requires-Dist: trytond<7.9,>=7.8
Provides-Extra: test
Requires-Dist: proteus<7.9,>=7.8; extra == "test"
Requires-Dist: trytond_account_payment_clearing<7.9,>=7.8; extra == "test"
Requires-Dist: trytond_carrier<7.9,>=7.8; extra == "test"
Requires-Dist: trytond_customs<7.9,>=7.8; extra == "test"
Requires-Dist: trytond_product_image<7.9,>=7.8; extra == "test"
Requires-Dist: trytond_product_image_attribute<7.9,>=7.8; extra == "test"
Requires-Dist: trytond_product_kit<7.9,>=7.8; extra == "test"
Requires-Dist: trytond_product_measurements<7.9,>=7.8; extra == "test"
Requires-Dist: trytond_sale_discount<7.9,>=7.8; extra == "test"
Requires-Dist: trytond_sale_invoice_grouping<7.9,>=7.8; extra == "test"
Requires-Dist: trytond_sale_secondary_unit<7.9,>=7.8; extra == "test"
Requires-Dist: trytond_sale_shipment_cost<7.9,>=7.8; extra == "test"
Requires-Dist: trytond_stock_package_shipping<7.9,>=7.8; extra == "test"
Requires-Dist: trytond_party[phonenumbers]<7.9,>=7.8; extra == "test"
Dynamic: author
Dynamic: author-email
Dynamic: classifier
Dynamic: description
Dynamic: download-url
Dynamic: home-page
Dynamic: keywords
Dynamic: license
Dynamic: license-file
Dynamic: project-url
Dynamic: provides-extra
Dynamic: requires-dist
Dynamic: requires-python
Dynamic: summary
